{
    "title": "Kevin Fang",
    "author": {
      "name": "Kevin Fang",
      "summary": "| birds of feather SSH.useFlock together",
      "social": {
        "twitter": "",
        "github": "thesnakefang",
        "email": "kevinfang@cmu.edu",
        "linkedin": "hirekevinfang",
        "facebook": "",
        "instagram": "kevinfang.tech"
      }
    },
    "description": "Kevin's collection of random scribblings",
    "siteUrl": "https://blog.kevinfang.tech",
    "disqusShortname": "kevinfang"
  }
  